{
  "weeks": [
    {
      "id": 1,
      "module": "一·导论",
      "mode": "讲授与实操",
      "title": "翻译本质界定与语料库设计",
      "summary": "用凉茶日本市场受阻案例引入课程，讨论翻译不是语言替换，而是市场、文化、体裁和受众共同制约下的再表达。",
      "route": "week1",
      "status": "ready"
    },
    {
      "id": 2,
      "module": "二·社交与致辞",
      "mode": "讲授与实操",
      "title": "致辞翻译与敬语层级",
      "summary": "准备企业年会主持稿与学生发言稿两组对比样本，训练受众身份、场合等级和敬语方向判断。",
      "route": "week2",
      "status": "ready"
    },
    {
      "id": 3,
      "module": "三·网络与游戏",
      "mode": "讲授与实操",
      "title": "游戏本地化完整流程",
      "summary": "以《黑神话：悟空》等游戏文本引入，理解翻译、润色、测试、术语表和角色语气管理的完整流程。",
      "route": "week3",
      "status": "ready"
    },
    {
      "id": 4,
      "module": "三·网络与游戏",
      "mode": "点评与补充",
      "title": "UI 空间限制与字符控制",
      "summary": "以学生第3周作业为材料，逐句点评按钮、菜单、技能、道具和台词在 UI 空间限制下的极限缩减技巧。",
      "route": "week4",
      "status": "ready"
    },
    {
      "id": 5,
      "module": "四·广告与营销",
      "mode": "讲授与实操",
      "title": "广告语言与 SEO 搜索词重构",
      "summary": "选取 iPhone 广告作为导入，分析キャッチフレーズ、品牌语气和中日关键词策略的跨文化重构。",
      "route": "week5",
      "status": "ready"
    },
    {
      "id": 6,
      "module": "四·广告与营销",
      "mode": "点评与补充",
      "title": "跨境电商标题与促销文案",
      "summary": "以上周广告作业为点评主材料，把年龄段、心理诉求、行业卖点和合规红线转化为电商 listing 操作框架。",
      "route": "week6",
      "status": "ready"
    },
    {
      "id": 7,
      "module": "五·旅游外宣",
      "mode": "讲授与实操",
      "title": "旅游文体的跨文化交际属性",
      "summary": "选取广东或广州景点中文介绍作为素材，比较推介语、说明语、公共标识和体验型文案的日译策略。",
      "route": "week7",
      "status": "ready"
    },
    {
      "id": 8,
      "module": "五·旅游外宣",
      "mode": "点评与补充",
      "title": "景物描写中的视点差异",
      "summary": "以学生第7周旅游外宣作业为材料，处理中文主观铺陈与日文客观说明之间的视点转换。",
      "route": "week8",
      "status": "ready"
    },
    {
      "id": 9,
      "module": "六·新闻报道",
      "mode": "讲授与实操",
      "title": "新闻 5W1H 与信息结构重编",
      "summary": "选取进行中的中日新闻事件，训练标题、导语、消息来源、数字日期和逆金字塔结构的中日转换。",
      "route": "week9",
      "status": "ready"
    },
    {
      "id": 10,
      "module": "六·新闻报道",
      "mode": "点评与考核",
      "title": "新闻作业点评与期中项目",
      "summary": "围绕新闻翻译作业共性错误做诊断，说明期中项目的材料选择、译文说明和评价标准。",
      "route": "week10",
      "status": "ready"
    },
    {
      "id": 11,
      "module": "七·科技产品",
      "mode": "讲授与实操",
      "title": "技术文档与说明书规范",
      "summary": "以扫地机器人和技术说明书为语料，建立技术文档类型、科技日语特征、术语调查和说明书规范意识。",
      "route": "week11",
      "status": "ready"
    },
    {
      "id": 12,
      "module": "七·科技产品",
      "mode": "点评与补充",
      "title": "MTPE 流程与质量评估",
      "summary": "以学生 MT 初译和人工编辑作业为起点，比较模型译文、CAT 工具、术语库和技术翻译中的风险项。",
      "route": "week12",
      "status": "ready"
    },
    {
      "id": 13,
      "module": "八·商务信函",
      "mode": "讲授与实操",
      "title": "商务文书的体裁转换",
      "summary": "通过中标通知、催款函、价格调整通知三个业务场景，训练中文业务信息到日语商务文书的转换。",
      "route": "week13",
      "status": "ready"
    },
    {
      "id": 14,
      "module": "八·商务信函",
      "mode": "点评与补充",
      "title": "拒绝与致歉信函的社交距离",
      "summary": "以第13周作业为点评主材料，训练拒绝、致歉、催促和说明责任时的缓冲表达与事实保留。",
      "route": "week14",
      "status": "ready"
    },
    {
      "id": 15,
      "module": "九·法规合同",
      "mode": "讲授与实操",
      "title": "涉外商业契约翻译（二）",
      "summary": "以一词之差的百万索赔案例导入，拆解条件嵌套、法律拟制、防御性表述和词汇技法。",
      "route": "week15",
      "status": "ready"
    },
    {
      "id": 16,
      "module": "九·法规合同",
      "mode": "点评与总结",
      "title": "合同翻译点评与能力回顾",
      "summary": "以第15周合同作业点评为主，回扣第1周翻译本质，完成全学期能力复盘与后续学习计划。",
      "route": "week16",
      "status": "ready"
    }
  ],
  "knowledge_points": [],
  "knowledge_edges": []
}